Workbook

Sheet Inputs
B2: ABS WATERFALL MODEL
B3: Change yellow cells to run scenarios
B5: POOL | C5: Value
B6: Pool Balance | C6: 100000000
B7: WAC | C7: 0.08
B8: WAM (months) | C8: 60
B9: CPR | C9: 0.1
B10: CDR | C10: 0.02 | D10: <-- CHANGE THIS (try 0.02, 0.05, 0.08)
B11: Severity | C11: 0.4
B13: TRANCHES | C13: Size % | D13: Coupon
B14: Tranche A (Senior) | C14: 0.8 | D14: 0.05
B15: Tranche B (Mezz) | C15: 0.12 | D15: 0.07
B16: Tranche C (Junior) | C16: 0.05 | D16: 0.1
B17: Equity/Residual | C17: =1-C14-C15-C16 -> 0 | D17: N/A
B19: CNL Trigger | C19: 0.05
B20: ARD (month) | C20: 36
B21: Trust Expense % | C21: 0.005 | D21: <-- Annual % of pool (servicing, trustee)
B22: Price A | C22: 98
B23: Price B | C23: 90
B24: Price C | C24: 70
B26: OC TARGETS | C26: Target
B27: A OC Target | C27: 1 | D27: <-- Pool ≥ A×Target to pay B int
B28: B OC Target | C28: 1.05 | D28: <-- Pool ≥ (A+B)×Target to pay C int
B29: C OC Target | C29: 1.15 | D29: <-- Pool ≥ (A+B+C)×Target for excess
B31: Force A OC Fail? | C31: No | D31: <-- Set to "Yes" to see lockouts/cures
B33: EXCESS SPREAD ANALYSIS
B34: Asset Yield (WAC) | C34: =$C$7 -> 0 | D34: <-- What borrowers pay
B35: Liability Cost:
B36: A Coupon × A Size | C36: =$D$14*$C$14 -> 0
B37: B Coupon × B Size | C37: =$D$15*$C$15 -> 0
B38: C Coupon × C Size | C38: =$D$16*$C$16 -> 0
B39: Wtd Avg Coupon (WAC Liab) | C39: =C36+C37+C38 -> 0 | D39: <-- What tranches are owed
B41: EXCESS SPREAD (annual) | C41: =C34-C39 -> 0
B42: Monthly Excess ($) | C42: =$C$6*C41/12 -> 0 | D42: On initial balance
B44: EXCESS SPREAD: The "cushion" between asset yield and liability cost. In normal times → flows to equity/residual. In turbo mode → redirected to pay down senior principal faster.

Sheet Asset Side
A1: Month | B1: Pool Bal | C1: Level Pay | D1: Sched Pmt | E1: Sched Int | F1: Sched Prin | G1: Prepay | H1: Default | I1: Loss | J1: Int Coll | K1: Prin Coll | L1: Cum Loss | M1: CNL% | N1: Date
A2: 0 | B2: =Inputs!$C$6 -> 0 | C2: =-PMT(Inputs!$C$7/12, Inputs!$C$8, Inputs!$C$6) -> 0 | D2: 0 | E2: 0 | F2: 0 | G2: 0 | H2: 0 | I2: 0 | J2: 0 | K2: 0 | L2: 0 | M2: 0 | N2: =DATE(2025,1,1) -> 0
A3: 1 | B3: =MAX(0, B2-F3-G3-H3) -> 0 | C3: =IF(B2-H3>0, -PMT(Inputs!$C$7/12, MAX(1, Inputs!$C$8-A3+1), B2-H3), 0) -> 0 | D3: =C3 -> 0 | E3: =(B2-H3)*Inputs!$C$7/12 -> 0 | F3: =IF(B2-H3>0, MIN(B2-H3, MAX(0, D3-E3)), 0) -> 0 | G3: =MAX(0, (B2-H3-F3))*(1-(1-Inputs!$C$9)^(1/12)) -> 0 | H3: =B2*(1-(1-Inputs!$C$10)^(1/12)) -> 0 | I3: =H3*Inputs!$C$11 -> 0 | J3: =E3 -> 0 | K3: =F3+G3+H3*(1-Inputs!$C$11) -> 0 | L3: =L2+I3 -> 0 | M3: =L3/Inputs!$C$6 -> 0 | N3: =EDATE($N$2, A3) -> 0
A4: 2 | B4: =MAX(0, B3-F4-G4-H4) -> 0 | C4: =IF(B3-H4>0, -PMT(Inputs!$C$7/12, MAX(1, Inputs!$C$8-A4+1), B3-H4), 0) -> 0 | D4: =C4 -> 0 | E4: =(B3-H4)*Inputs!$C$7/12 -> 0 | F4: =IF(B3-H4>0, MIN(B3-H4, MAX(0, D4-E4)), 0) -> 0 | G4: =MAX(0, (B3-H4-F4))*(1-(1-Inputs!$C$9)^(1/12)) -> 0 | H4: =B3*(1-(1-Inputs!$C$10)^(1/12)) -> 0 | I4: =H4*Inputs!$C$11 -> 0 | J4: =E4 -> 0 | K4: =F4+G4+H4*(1-Inputs!$C$11) -> 0 | L4: =L3+I4 -> 0 | M4: =L4/Inputs!$C$6 -> 0 | N4: =EDATE($N$2, A4) -> 0
A5: 3 | B5: =MAX(0, B4-F5-G5-H5) -> 0 | C5: =IF(B4-H5>0, -PMT(Inputs!$C$7/12, MAX(1, Inputs!$C$8-A5+1), B4-H5), 0) -> 0 | D5: =C5 -> 0 | E5: =(B4-H5)*Inputs!$C$7/12 -> 0 | F5: =IF(B4-H5>0, MIN(B4-H5, MAX(0, D5-E5)), 0) -> 0 | G5: =MAX(0, (B4-H5-F5))*(1-(1-Inputs!$C$9)^(1/12)) -> 0 | H5: =B4*(1-(1-Inputs!$C$10)^(1/12)) -> 0 | I5: =H5*Inputs!$C$11 -> 0 | J5: =E5 -> 0 | K5: =F5+G5+H5*(1-Inputs!$C$11) -> 0 | L5: =L4+I5 -> 0 | M5: =L5/Inputs!$C$6 -> 0 | N5: =EDATE($N$2, A5) -> 0
A6: 4 | B6: =MAX(0, B5-F6-G6-H6) -> 0 | C6: =IF(B5-H6>0, -PMT(Inputs!$C$7/12, MAX(1, Inputs!$C$8-A6+1), B5-H6), 0) -> 0 | D6: =C6 -> 0 | E6: =(B5-H6)*Inputs!$C$7/12 -> 0 | F6: =IF(B5-H6>0, MIN(B5-H6, MAX(0, D6-E6)), 0) -> 0 | G6: =MAX(0, (B5-H6-F6))*(1-(1-Inputs!$C$9)^(1/12)) -> 0 | H6: =B5*(1-(1-Inputs!$C$10)^(1/12)) -> 0 | I6: =H6*Inputs!$C$11 -> 0 | J6: =E6 -> 0 | K6: =F6+G6+H6*(1-Inputs!$C$11) -> 0 | L6: =L5+I6 -> 0 | M6: =L6/Inputs!$C$6 -> 0 | N6: =EDATE($N$2, A6) -> 0
A7: 5 | B7: =MAX(0, B6-F7-G7-H7) -> 0 | C7: =IF(B6-H7>0, -PMT(Inputs!$C$7/12, MAX(1, Inputs!$C$8-A7+1), B6-H7), 0) -> 0 | D7: =C7 -> 0 | E7: =(B6-H7)*Inputs!$C$7/12 -> 0 | F7: =IF(B6-H7>0, MIN(B6-H7, MAX(0, D7-E7)), 0) -> 0 | G7: =MAX(0, (B6-H7-F7))*(1-(1-Inputs!$C$9)^(1/12)) -> 0 | H7: =B6*(1-(1-Inputs!$C$10)^(1/12)) -> 0 | I7: =H7*Inputs!$C$11 -> 0 | J7: =E7 -> 0 | K7: =F7+G7+H7*(1-Inputs!$C$11) -> 0 | L7: =L6+I7 -> 0 | M7: =L7/Inputs!$C$6 -> 0 | N7: =EDATE($N$2, A7) -> 0
A8: 6 | B8: =MAX(0, B7-F8-G8-H8) -> 0 | C8: =IF(B7-H8>0, -PMT(Inputs!$C$7/12, MAX(1, Inputs!$C$8-A8+1), B7-H8), 0) -> 0 | D8: =C8 -> 0 | E8: =(B7-H8)*Inputs!$C$7/12 -> 0 | F8: =IF(B7-H8>0, MIN(B7-H8, MAX(0, D8-E8)), 0) -> 0 | G8: =MAX(0, (B7-H8-F8))*(1-(1-Inputs!$C$9)^(1/12)) -> 0 | H8: =B7*(1-(1-Inputs!$C$10)^(1/12)) -> 0 | I8: =H8*Inputs!$C$11 -> 0 | J8: =E8 -> 0 | K8: =F8+G8+H8*(1-Inputs!$C$11) -> 0 | L8: =L7+I8 -> 0 | M8: =L8/Inputs!$C$6 -> 0 | N8: =EDATE($N$2, A8) -> 0
A9: 7 | B9: =MAX(0, B8-F9-G9-H9) -> 0 | C9: =IF(B8-H9>0, -PMT(Inputs!$C$7/12, MAX(1, Inputs!$C$8-A9+1), B8-H9), 0) -> 0 | D9: =C9 -> 0 | E9: =(B8-H9)*Inputs!$C$7/12 -> 0 | F9: =IF(B8-H9>0, MIN(B8-H9, MAX(0, D9-E9)), 0) -> 0 | G9: =MAX(0, (B8-H9-F9))*(1-(1-Inputs!$C$9)^(1/12)) -> 0 | H9: =B8*(1-(1-Inputs!$C$10)^(1/12)) -> 0 | I9: =H9*Inputs!$C$11 -> 0 | J9: =E9 -> 0 | K9: =F9+G9+H9*(1-Inputs!$C$11) -> 0 | L9: =L8+I9 -> 0 | M9: =L9/Inputs!$C$6 -> 0 | N9: =EDATE($N$2, A9) -> 0
A10: 8 | B10: =MAX(0, B9-F10-G10-H10) -> 0 | C10: =IF(B9-H10>0, -PMT(Inputs!$C$7/12, MAX(1, Inputs!$C$8-A10+1), B9-H10), 0) -> 0 | D10: =C10 -> 0 | E10: =(B9-H10)*Inputs!$C$7/12 -> 0 | F10: =IF(B9-H10>0, MIN(B9-H10, MAX(0, D10-E10)), 0) -> 0 | G10: =MAX(0, (B9-H10-F10))*(1-(1-Inputs!$C$9)^(1/12)) -> 0 | H10: =B9*(1-(1-Inputs!$C$10)^(1/12)) -> 0 | I10: =H10*Inputs!$C$11 -> 0 | J10: =E10 -> 0 | K10: =F10+G10+H10*(1-Inputs!$C$11) -> 0 | L10: =L9+I10 -> 0 | M10: =L10/Inputs!$C$6 -> 0 | N10: =EDATE($N$2, A10) -> 0
A11: 9 | B11: =MAX(0, B10-F11-G11-H11) -> 0 | C11: =IF(B10-H11>0, -PMT(Inputs!$C$7/12, MAX(1, Inputs!$C$8-A11+1), B10-H11), 0) -> 0 | D11: =C11 -> 0 | E11: =(B10-H11)*Inputs!$C$7/12 -> 0 | F11: =IF(B10-H11>0, MIN(B10-H11, MAX(0, D11-E11)), 0) -> 0 | G11: =MAX(0, (B10-H11-F11))*(1-(1-Inputs!$C$9)^(1/12)) -> 0 | H11: =B10*(1-(1-Inputs!$C$10)^(1/12)) -> 0 | I11: =H11*Inputs!$C$11 -> 0 | J11: =E11 -> 0 | K11: =F11+G11+H11*(1-Inputs!$C$11) -> 0 | L11: =L10+I11 -> 0 | M11: =L11/Inputs!$C$6 -> 0 | N11: =EDATE($N$2, A11) -> 0
A12: 10 | B12: =MAX(0, B11-F12-G12-H12) -> 0 | C12: =IF(B11-H12>0, -PMT(Inputs!$C$7/12, MAX(1, Inputs!$C$8-A12+1), B11-H12), 0) -> 0 | D12: =C12 -> 0 | E12: =(B11-H12)*Inputs!$C$7/12 -> 0 | F12: =IF(B11-H12>0, MIN(B11-H12, MAX(0, D12-E12)), 0) -> 0 | G12: =MAX(0, (B11-H12-F12))*(1-(1-Inputs!$C$9)^(1/12)) -> 0 | H12: =B11*(1-(1-Inputs!$C$10)^(1/12)) -> 0 | I12: =H12*Inputs!$C$11 -> 0 | J12: =E12 -> 0 | K12: =F12+G12+H12*(1-Inputs!$C$11) -> 0 | L12: =L11+I12 -> 0 | M12: =L12/Inputs!$C$6 -> 0 | N12: =EDATE($N$2, A12) -> 0
A13: 11 | B13: =MAX(0, B12-F13-G13-H13) -> 0 | C13: =IF(B12-H13>0, -PMT(Inputs!$C$7/12, MAX(1, Inputs!$C$8-A13+1), B12-H13), 0) -> 0 | D13: =C13 -> 0 | E13: =(B12-H13)*Inputs!$C$7/12 -> 0 | F13: =IF(B12-H13>0, MIN(B12-H13, MAX(0, D13-E13)), 0) -> 0 | G13: =MAX(0, (B12-H13-F13))*(1-(1-Inputs!$C$9)^(1/12)) -> 0 | H13: =B12*(1-(1-Inputs!$C$10)^(1/12)) -> 0 | I13: =H13*Inputs!$C$11 -> 0 | J13: =E13 -> 0 | K13: =F13+G13+H13*(1-Inputs!$C$11) -> 0 | L13: =L12+I13 -> 0 | M13: =L13/Inputs!$C$6 -> 0 | N13: =EDATE($N$2, A13) -> 0
A14: 12 | B14: =MAX(0, B13-F14-G14-H14) -> 0 | C14: =IF(B13-H14>0, -PMT(Inputs!$C$7/12, MAX(1, Inputs!$C$8-A14+1), B13-H14), 0) -> 0 | D14: =C14 -> 0 | E14: =(B13-H14)*Inputs!$C$7/12 -> 0 | F14: =IF(B13-H14>0, MIN(B13-H14, MAX(0, D14-E14)), 0) -> 0 | G14: =MAX(0, (B13-H14-F14))*(1-(1-Inputs!$C$9)^(1/12)) -> 0 | H14: =B13*(1-(1-Inputs!$C$10)^(1/12)) -> 0 | I14: =H14*Inputs!$C$11 -> 0 | J14: =E14 -> 0 | K14: =F14+G14+H14*(1-Inputs!$C$11) -> 0 | L14: =L13+I14 -> 0 | M14: =L14/Inputs!$C$6 -> 0 | N14: =EDATE($N$2, A14) -> 0
... A82: 80 | B82: =MAX(0, B81-F82-G82-H82) -> 0 | C82: =IF(B81-H82>0, -PMT(Inputs!$C$7/12, MAX(1, Inputs!$C$8-A82+1), B81-H82), 0) -> 0 | D82: =C82 -> 0 | E82: =(B81-H82)*Inputs!$C$7/12 -> 0 | F82: =IF(B81-H82>0, MIN(B81-H82, MAX(0, D82-E82)), 0) -> 0 | G82: =MAX(0, (B81-H82-F82))*(1-(1-Inputs!$C$9)^(1/12)) -> 0 | H82: =B81*(1-(1-Inputs!$C$10)^(1/12)) -> 0 | I82: =H82*Inputs!$C$11 -> 0 | J82: =E82 -> 0 | K82: =F82+G82+H82*(1-Inputs!$C$11) -> 0 | L82: =L81+I82 -> 0 | M82: =L82/Inputs!$C$6 -> 0 | N82: =EDATE($N$2, A82) -> 0

Sheet Waterfall
A1: Month | B1: Pool Beg | C1: Avail Funds | D1: Expenses | E1: A OC? | F1: A Int Pd | G1: A Prin Pd | H1: A Bal | I1: B OC? | J1: B Int Pd | K1: B Prin Pd | L1: B Bal | M1: C OC? | N1: C Int Pd | O1: C Prin Pd | P1: C Bal | Q1: Excess | R1: Equity | S1: Check | T1: Date | U1: A CF | V1: B CF | W1: C CF
A2: 0 | B2: ='Asset Side'!B2 -> 0 | C2: 0 | D2: 0 | E2: N/A | F2: 0 | G2: 0 | H2: =Inputs!$C$6*Inputs!$C$14 -> 0 | I2: N/A | J2: 0 | K2: 0 | L2: =Inputs!$C$6*Inputs!$C$15 -> 0 | M2: N/A | N2: 0 | O2: 0 | P2: =Inputs!$C$6*Inputs!$C$16 -> 0 | Q2: 0 | R2: 0 | S2: OK | T2: =DATE(2025,1,1) -> 0 | U2: =-Inputs!$C$6*Inputs!$C$14*Inputs!$C$22/100 -> 0 | V2: =-Inputs!$C$6*Inputs!$C$15*Inputs!$C$23/100 -> 0 | W2: =-Inputs!$C$6*Inputs!$C$16*Inputs!$C$24/100 -> 0
A3: 1 | B3: ='Asset Side'!B2 -> 0 | C3: ='Asset Side'!J3+'Asset Side'!K3 -> 0 | D3: =MIN(C3, B2*Inputs!$C$21/12) -> 0 | E3: =IF(AND(B3 >= H2*Inputs!$C$27, Inputs!$C$31<>"Yes"), TRUE, FALSE) -> 0 | F3: =MIN(H2*Inputs!$D$14/12, MAX(0, C3 - D3)) -> 0 | G3: =MIN(H2, MAX(0, C3 - D3 - F3 - J3 - N3)) -> 0 | H3: =MAX(0, H2 - G3) -> 0 | I3: =IF(B3 >= (H2+L2)*Inputs!$C$28, TRUE, FALSE) -> 0 | J3: =IF(AND(E3=TRUE, A3<=Inputs!$C$20), MIN(L2*Inputs!$D$15/12, MAX(0, C3 - D3 - F3)), 0) -> 0 | K3: =IF(H3=0, MIN(L2, MAX(0, C3 - D3 - F3 - J3 - N3 - G3)), 0) -> 0 | L3: =MAX(0, L2 - K3) -> 0 | M3: =IF(B3 >= (H2+L2+P2)*Inputs!$C$29, TRUE, FALSE) -> 0 | N3: =IF(AND(I3=TRUE, A3<=Inputs!$C$20), MIN(P2*Inputs!$D$16/12, MAX(0, C3 - D3 - F3 - J3)), 0) -> 0 | O3: =IF(AND(H3=0, L3=0), MIN(P2, MAX(0, C3 - D3 - F3 - J3 - N3 - G3 - K3)), 0) -> 0 | P3: =MAX(0, P2 - O3) -> 0 | Q3: =IF(AND(E3=TRUE, I3=TRUE, M3=TRUE, A3<=Inputs!$C$20), R3, 0) -> 0 | R3: =MAX(0, C3 - D3 - F3 - J3 - N3 - G3 - K3 - O3) -> 0 | S3: =IF(ABS(D3+(F3+J3+N3)+(G3+K3+O3)+R3-C3)<1, "OK", "ERR") -> 0 | T3: =EDATE($T$2, A3) -> 0 | U3: =F3+G3 -> 0 | V3: =J3+K3 -> 0 | W3: =N3+O3 -> 0
A4: 2 | B4: ='Asset Side'!B3 -> 0 | C4: ='Asset Side'!J4+'Asset Side'!K4 -> 0 | D4: =MIN(C4, B3*Inputs!$C$21/12) -> 0 | E4: =IF(AND(B4 >= H3*Inputs!$C$27, Inputs!$C$31<>"Yes"), TRUE, FALSE) -> 0 | F4: =MIN(H3*Inputs!$D$14/12, MAX(0, C4 - D4)) -> 0 | G4: =MIN(H3, MAX(0, C4 - D4 - F4 - J4 - N4)) -> 0 | H4: =MAX(0, H3 - G4) -> 0 | I4: =IF(B4 >= (H3+L3)*Inputs!$C$28, TRUE, FALSE) -> 0 | J4: =IF(AND(E4=TRUE, A4<=Inputs!$C$20), MIN(L3*Inputs!$D$15/12, MAX(0, C4 - D4 - F4)), 0) -> 0 | K4: =IF(H4=0, MIN(L3, MAX(0, C4 - D4 - F4 - J4 - N4 - G4)), 0) -> 0 | L4: =MAX(0, L3 - K4) -> 0 | M4: =IF(B4 >= (H3+L3+P3)*Inputs!$C$29, TRUE, FALSE) -> 0 | N4: =IF(AND(I4=TRUE, A4<=Inputs!$C$20), MIN(P3*Inputs!$D$16/12, MAX(0, C4 - D4 - F4 - J4)), 0) -> 0 | O4: =IF(AND(H4=0, L4=0), MIN(P3, MAX(0, C4 - D4 - F4 - J4 - N4 - G4 - K4)), 0) -> 0 | P4: =MAX(0, P3 - O4) -> 0 | Q4: =IF(AND(E4=TRUE, I4=TRUE, M4=TRUE, A4<=Inputs!$C$20), R4, 0) -> 0 | R4: =MAX(0, C4 - D4 - F4 - J4 - N4 - G4 - K4 - O4) -> 0 | S4: =IF(ABS(D4+(F4+J4+N4)+(G4+K4+O4)+R4-C4)<1, "OK", "ERR") -> 0 | T4: =EDATE($T$2, A4) -> 0 | U4: =F4+G4 -> 0 | V4: =J4+K4 -> 0 | W4: =N4+O4 -> 0
A5: 3 | B5: ='Asset Side'!B4 -> 0 | C5: ='Asset Side'!J5+'Asset Side'!K5 -> 0 | D5: =MIN(C5, B4*Inputs!$C$21/12) -> 0 | E5: =IF(AND(B5 >= H4*Inputs!$C$27, Inputs!$C$31<>"Yes"), TRUE, FALSE) -> 0 | F5: =MIN(H4*Inputs!$D$14/12, MAX(0, C5 - D5)) -> 0 | G5: =MIN(H4, MAX(0, C5 - D5 - F5 - J5 - N5)) -> 0 | H5: =MAX(0, H4 - G5) -> 0 | I5: =IF(B5 >= (H4+L4)*Inputs!$C$28, TRUE, FALSE) -> 0 | J5: =IF(AND(E5=TRUE, A5<=Inputs!$C$20), MIN(L4*Inputs!$D$15/12, MAX(0, C5 - D5 - F5)), 0) -> 0 | K5: =IF(H5=0, MIN(L4, MAX(0, C5 - D5 - F5 - J5 - N5 - G5)), 0) -> 0 | L5: =MAX(0, L4 - K5) -> 0 | M5: =IF(B5 >= (H4+L4+P4)*Inputs!$C$29, TRUE, FALSE) -> 0 | N5: =IF(AND(I5=TRUE, A5<=Inputs!$C$20), MIN(P4*Inputs!$D$16/12, MAX(0, C5 - D5 - F5 - J5)), 0) -> 0 | O5: =IF(AND(H5=0, L5=0), MIN(P4, MAX(0, C5 - D5 - F5 - J5 - N5 - G5 - K5)), 0) -> 0 | P5: =MAX(0, P4 - O5) -> 0 | Q5: =IF(AND(E5=TRUE, I5=TRUE, M5=TRUE, A5<=Inputs!$C$20), R5, 0) -> 0 | R5: =MAX(0, C5 - D5 - F5 - J5 - N5 - G5 - K5 - O5) -> 0 | S5: =IF(ABS(D5+(F5+J5+N5)+(G5+K5+O5)+R5-C5)<1, "OK", "ERR") -> 0 | T5: =EDATE($T$2, A5) -> 0 | U5: =F5+G5 -> 0 | V5: =J5+K5 -> 0 | W5: =N5+O5 -> 0
A6: 4 | B6: ='Asset Side'!B5 -> 0 | C6: ='Asset Side'!J6+'Asset Side'!K6 -> 0 | D6: =MIN(C6, B5*Inputs!$C$21/12) -> 0 | E6: =IF(AND(B6 >= H5*Inputs!$C$27, Inputs!$C$31<>"Yes"), TRUE, FALSE) -> 0 | F6: =MIN(H5*Inputs!$D$14/12, MAX(0, C6 - D6)) -> 0 | G6: =MIN(H5, MAX(0, C6 - D6 - F6 - J6 - N6)) -> 0 | H6: =MAX(0, H5 - G6) -> 0 | I6: =IF(B6 >= (H5+L5)*Inputs!$C$28, TRUE, FALSE) -> 0 | J6: =IF(AND(E6=TRUE, A6<=Inputs!$C$20), MIN(L5*Inputs!$D$15/12, MAX(0, C6 - D6 - F6)), 0) -> 0 | K6: =IF(H6=0, MIN(L5, MAX(0, C6 - D6 - F6 - J6 - N6 - G6)), 0) -> 0 | L6: =MAX(0, L5 - K6) -> 0 | M6: =IF(B6 >= (H5+L5+P5)*Inputs!$C$29, TRUE, FALSE) -> 0 | N6: =IF(AND(I6=TRUE, A6<=Inputs!$C$20), MIN(P5*Inputs!$D$16/12, MAX(0, C6 - D6 - F6 - J6)), 0) -> 0 | O6: =IF(AND(H6=0, L6=0), MIN(P5, MAX(0, C6 - D6 - F6 - J6 - N6 - G6 - K6)), 0) -> 0 | P6: =MAX(0, P5 - O6) -> 0 | Q6: =IF(AND(E6=TRUE, I6=TRUE, M6=TRUE, A6<=Inputs!$C$20), R6, 0) -> 0 | R6: =MAX(0, C6 - D6 - F6 - J6 - N6 - G6 - K6 - O6) -> 0 | S6: =IF(ABS(D6+(F6+J6+N6)+(G6+K6+O6)+R6-C6)<1, "OK", "ERR") -> 0 | T6: =EDATE($T$2, A6) -> 0 | U6: =F6+G6 -> 0 | V6: =J6+K6 -> 0 | W6: =N6+O6 -> 0
A7: 5 | B7: ='Asset Side'!B6 -> 0 | C7: ='Asset Side'!J7+'Asset Side'!K7 -> 0 | D7: =MIN(C7, B6*Inputs!$C$21/12) -> 0 | E7: =IF(AND(B7 >= H6*Inputs!$C$27, Inputs!$C$31<>"Yes"), TRUE, FALSE) -> 0 | F7: =MIN(H6*Inputs!$D$14/12, MAX(0, C7 - D7)) -> 0 | G7: =MIN(H6, MAX(0, C7 - D7 - F7 - J7 - N7)) -> 0 | H7: =MAX(0, H6 - G7) -> 0 | I7: =IF(B7 >= (H6+L6)*Inputs!$C$28, TRUE, FALSE) -> 0 | J7: =IF(AND(E7=TRUE, A7<=Inputs!$C$20), MIN(L6*Inputs!$D$15/12, MAX(0, C7 - D7 - F7)), 0) -> 0 | K7: =IF(H7=0, MIN(L6, MAX(0, C7 - D7 - F7 - J7 - N7 - G7)), 0) -> 0 | L7: =MAX(0, L6 - K7) -> 0 | M7: =IF(B7 >= (H6+L6+P6)*Inputs!$C$29, TRUE, FALSE) -> 0 | N7: =IF(AND(I7=TRUE, A7<=Inputs!$C$20), MIN(P6*Inputs!$D$16/12, MAX(0, C7 - D7 - F7 - J7)), 0) -> 0 | O7: =IF(AND(H7=0, L7=0), MIN(P6, MAX(0, C7 - D7 - F7 - J7 - N7 - G7 - K7)), 0) -> 0 | P7: =MAX(0, P6 - O7) -> 0 | Q7: =IF(AND(E7=TRUE, I7=TRUE, M7=TRUE, A7<=Inputs!$C$20), R7, 0) -> 0 | R7: =MAX(0, C7 - D7 - F7 - J7 - N7 - G7 - K7 - O7) -> 0 | S7: =IF(ABS(D7+(F7+J7+N7)+(G7+K7+O7)+R7-C7)<1, "OK", "ERR") -> 0 | T7: =EDATE($T$2, A7) -> 0 | U7: =F7+G7 -> 0 | V7: =J7+K7 -> 0 | W7: =N7+O7 -> 0
A8: 6 | B8: ='Asset Side'!B7 -> 0 | C8: ='Asset Side'!J8+'Asset Side'!K8 -> 0 | D8: =MIN(C8, B7*Inputs!$C$21/12) -> 0 | E8: =IF(AND(B8 >= H7*Inputs!$C$27, Inputs!$C$31<>"Yes"), TRUE, FALSE) -> 0 | F8: =MIN(H7*Inputs!$D$14/12, MAX(0, C8 - D8)) -> 0 | G8: =MIN(H7, MAX(0, C8 - D8 - F8 - J8 - N8)) -> 0 | H8: =MAX(0, H7 - G8) -> 0 | I8: =IF(B8 >= (H7+L7)*Inputs!$C$28, TRUE, FALSE) -> 0 | J8: =IF(AND(E8=TRUE, A8<=Inputs!$C$20), MIN(L7*Inputs!$D$15/12, MAX(0, C8 - D8 - F8)), 0) -> 0 | K8: =IF(H8=0, MIN(L7, MAX(0, C8 - D8 - F8 - J8 - N8 - G8)), 0) -> 0 | L8: =MAX(0, L7 - K8) -> 0 | M8: =IF(B8 >= (H7+L7+P7)*Inputs!$C$29, TRUE, FALSE) -> 0 | N8: =IF(AND(I8=TRUE, A8<=Inputs!$C$20), MIN(P7*Inputs!$D$16/12, MAX(0, C8 - D8 - F8 - J8)), 0) -> 0 | O8: =IF(AND(H8=0, L8=0), MIN(P7, MAX(0, C8 - D8 - F8 - J8 - N8 - G8 - K8)), 0) -> 0 | P8: =MAX(0, P7 - O8) -> 0 | Q8: =IF(AND(E8=TRUE, I8=TRUE, M8=TRUE, A8<=Inputs!$C$20), R8, 0) -> 0 | R8: =MAX(0, C8 - D8 - F8 - J8 - N8 - G8 - K8 - O8) -> 0 | S8: =IF(ABS(D8+(F8+J8+N8)+(G8+K8+O8)+R8-C8)<1, "OK", "ERR") -> 0 | T8: =EDATE($T$2, A8) -> 0 | U8: =F8+G8 -> 0 | V8: =J8+K8 -> 0 | W8: =N8+O8 -> 0
A9: 7 | B9: ='Asset Side'!B8 -> 0 | C9: ='Asset Side'!J9+'Asset Side'!K9 -> 0 | D9: =MIN(C9, B8*Inputs!$C$21/12) -> 0 | E9: =IF(AND(B9 >= H8*Inputs!$C$27, Inputs!$C$31<>"Yes"), TRUE, FALSE) -> 0 | F9: =MIN(H8*Inputs!$D$14/12, MAX(0, C9 - D9)) -> 0 | G9: =MIN(H8, MAX(0, C9 - D9 - F9 - J9 - N9)) -> 0 | H9: =MAX(0, H8 - G9) -> 0 | I9: =IF(B9 >= (H8+L8)*Inputs!$C$28, TRUE, FALSE) -> 0 | J9: =IF(AND(E9=TRUE, A9<=Inputs!$C$20), MIN(L8*Inputs!$D$15/12, MAX(0, C9 - D9 - F9)), 0) -> 0 | K9: =IF(H9=0, MIN(L8, MAX(0, C9 - D9 - F9 - J9 - N9 - G9)), 0) -> 0 | L9: =MAX(0, L8 - K9) -> 0 | M9: =IF(B9 >= (H8+L8+P8)*Inputs!$C$29, TRUE, FALSE) -> 0 | N9: =IF(AND(I9=TRUE, A9<=Inputs!$C$20), MIN(P8*Inputs!$D$16/12, MAX(0, C9 - D9 - F9 - J9)), 0) -> 0 | O9: =IF(AND(H9=0, L9=0), MIN(P8, MAX(0, C9 - D9 - F9 - J9 - N9 - G9 - K9)), 0) -> 0 | P9: =MAX(0, P8 - O9) -> 0 | Q9: =IF(AND(E9=TRUE, I9=TRUE, M9=TRUE, A9<=Inputs!$C$20), R9, 0) -> 0 | R9: =MAX(0, C9 - D9 - F9 - J9 - N9 - G9 - K9 - O9) -> 0 | S9: =IF(ABS(D9+(F9+J9+N9)+(G9+K9+O9)+R9-C9)<1, "OK", "ERR") -> 0 | T9: =EDATE($T$2, A9) -> 0 | U9: =F9+G9 -> 0 | V9: =J9+K9 -> 0 | W9: =N9+O9 -> 0
A10: 8 | B10: ='Asset Side'!B9 -> 0 | C10: ='Asset Side'!J10+'Asset Side'!K10 -> 0 | D10: =MIN(C10, B9*Inputs!$C$21/12) -> 0 | E10: =IF(AND(B10 >= H9*Inputs!$C$27, Inputs!$C$31<>"Yes"), TRUE, FALSE) -> 0 | F10: =MIN(H9*Inputs!$D$14/12, MAX(0, C10 - D10)) -> 0 | G10: =MIN(H9, MAX(0, C10 - D10 - F10 - J10 - N10)) -> 0 | H10: =MAX(0, H9 - G10) -> 0 | I10: =IF(B10 >= (H9+L9)*Inputs!$C$28, TRUE, FALSE) -> 0 | J10: =IF(AND(E10=TRUE, A10<=Inputs!$C$20), MIN(L9*Inputs!$D$15/12, MAX(0, C10 - D10 - F10)), 0) -> 0 | K10: =IF(H10=0, MIN(L9, MAX(0, C10 - D10 - F10 - J10 - N10 - G10)), 0) -> 0 | L10: =MAX(0, L9 - K10) -> 0 | M10: =IF(B10 >= (H9+L9+P9)*Inputs!$C$29, TRUE, FALSE) -> 0 | N10: =IF(AND(I10=TRUE, A10<=Inputs!$C$20), MIN(P9*Inputs!$D$16/12, MAX(0, C10 - D10 - F10 - J10)), 0) -> 0 | O10: =IF(AND(H10=0, L10=0), MIN(P9, MAX(0, C10 - D10 - F10 - J10 - N10 - G10 - K10)), 0) -> 0 | P10: =MAX(0, P9 - O10) -> 0 | Q10: =IF(AND(E10=TRUE, I10=TRUE, M10=TRUE, A10<=Inputs!$C$20), R10, 0) -> 0 | R10: =MAX(0, C10 - D10 - F10 - J10 - N10 - G10 - K10 - O10) -> 0 | S10: =IF(ABS(D10+(F10+J10+N10)+(G10+K10+O10)+R10-C10)<1, "OK", "ERR") -> 0 | T10: =EDATE($T$2, A10) -> 0 | U10: =F10+G10 -> 0 | V10: =J10+K10 -> 0 | W10: =N10+O10 -> 0
A11: 9 | B11: ='Asset Side'!B10 -> 0 | C11: ='Asset Side'!J11+'Asset Side'!K11 -> 0 | D11: =MIN(C11, B10*Inputs!$C$21/12) -> 0 | E11: =IF(AND(B11 >= H10*Inputs!$C$27, Inputs!$C$31<>"Yes"), TRUE, FALSE) -> 0 | F11: =MIN(H10*Inputs!$D$14/12, MAX(0, C11 - D11)) -> 0 | G11: =MIN(H10, MAX(0, C11 - D11 - F11 - J11 - N11)) -> 0 | H11: =MAX(0, H10 - G11) -> 0 | I11: =IF(B11 >= (H10+L10)*Inputs!$C$28, TRUE, FALSE) -> 0 | J11: =IF(AND(E11=TRUE, A11<=Inputs!$C$20), MIN(L10*Inputs!$D$15/12, MAX(0, C11 - D11 - F11)), 0) -> 0 | K11: =IF(H11=0, MIN(L10, MAX(0, C11 - D11 - F11 - J11 - N11 - G11)), 0) -> 0 | L11: =MAX(0, L10 - K11) -> 0 | M11: =IF(B11 >= (H10+L10+P10)*Inputs!$C$29, TRUE, FALSE) -> 0 | N11: =IF(AND(I11=TRUE, A11<=Inputs!$C$20), MIN(P10*Inputs!$D$16/12, MAX(0, C11 - D11 - F11 - J11)), 0) -> 0 | O11: =IF(AND(H11=0, L11=0), MIN(P10, MAX(0, C11 - D11 - F11 - J11 - N11 - G11 - K11)), 0) -> 0 | P11: =MAX(0, P10 - O11) -> 0 | Q11: =IF(AND(E11=TRUE, I11=TRUE, M11=TRUE, A11<=Inputs!$C$20), R11, 0) -> 0 | R11: =MAX(0, C11 - D11 - F11 - J11 - N11 - G11 - K11 - O11) -> 0 | S11: =IF(ABS(D11+(F11+J11+N11)+(G11+K11+O11)+R11-C11)<1, "OK", "ERR") -> 0 | T11: =EDATE($T$2, A11) -> 0 | U11: =F11+G11 -> 0 | V11: =J11+K11 -> 0 | W11: =N11+O11 -> 0
A12: 10 | B12: ='Asset Side'!B11 -> 0 | C12: ='Asset Side'!J12+'Asset Side'!K12 -> 0 | D12: =MIN(C12, B11*Inputs!$C$21/12) -> 0 | E12: =IF(AND(B12 >= H11*Inputs!$C$27, Inputs!$C$31<>"Yes"), TRUE, FALSE) -> 0 | F12: =MIN(H11*Inputs!$D$14/12, MAX(0, C12 - D12)) -> 0 | G12: =MIN(H11, MAX(0, C12 - D12 - F12 - J12 - N12)) -> 0 | H12: =MAX(0, H11 - G12) -> 0 | I12: =IF(B12 >= (H11+L11)*Inputs!$C$28, TRUE, FALSE) -> 0 | J12: =IF(AND(E12=TRUE, A12<=Inputs!$C$20), MIN(L11*Inputs!$D$15/12, MAX(0, C12 - D12 - F12)), 0) -> 0 | K12: =IF(H12=0, MIN(L11, MAX(0, C12 - D12 - F12 - J12 - N12 - G12)), 0) -> 0 | L12: =MAX(0, L11 - K12) -> 0 | M12: =IF(B12 >= (H11+L11+P11)*Inputs!$C$29, TRUE, FALSE) -> 0 | N12: =IF(AND(I12=TRUE, A12<=Inputs!$C$20), MIN(P11*Inputs!$D$16/12, MAX(0, C12 - D12 - F12 - J12)), 0) -> 0 | O12: =IF(AND(H12=0, L12=0), MIN(P11, MAX(0, C12 - D12 - F12 - J12 - N12 - G12 - K12)), 0) -> 0 | P12: =MAX(0, P11 - O12) -> 0 | Q12: =IF(AND(E12=TRUE, I12=TRUE, M12=TRUE, A12<=Inputs!$C$20), R12, 0) -> 0 | R12: =MAX(0, C12 - D12 - F12 - J12 - N12 - G12 - K12 - O12) -> 0 | S12: =IF(ABS(D12+(F12+J12+N12)+(G12+K12+O12)+R12-C12)<1, "OK", "ERR") -> 0 | T12: =EDATE($T$2, A12) -> 0 | U12: =F12+G12 -> 0 | V12: =J12+K12 -> 0 | W12: =N12+O12 -> 0
A13: 11 | B13: ='Asset Side'!B12 -> 0 | C13: ='Asset Side'!J13+'Asset Side'!K13 -> 0 | D13: =MIN(C13, B12*Inputs!$C$21/12) -> 0 | E13: =IF(AND(B13 >= H12*Inputs!$C$27, Inputs!$C$31<>"Yes"), TRUE, FALSE) -> 0 | F13: =MIN(H12*Inputs!$D$14/12, MAX(0, C13 - D13)) -> 0 | G13: =MIN(H12, MAX(0, C13 - D13 - F13 - J13 - N13)) -> 0 | H13: =MAX(0, H12 - G13) -> 0 | I13: =IF(B13 >= (H12+L12)*Inputs!$C$28, TRUE, FALSE) -> 0 | J13: =IF(AND(E13=TRUE, A13<=Inputs!$C$20), MIN(L12*Inputs!$D$15/12, MAX(0, C13 - D13 - F13)), 0) -> 0 | K13: =IF(H13=0, MIN(L12, MAX(0, C13 - D13 - F13 - J13 - N13 - G13)), 0) -> 0 | L13: =MAX(0, L12 - K13) -> 0 | M13: =IF(B13 >= (H12+L12+P12)*Inputs!$C$29, TRUE, FALSE) -> 0 | N13: =IF(AND(I13=TRUE, A13<=Inputs!$C$20), MIN(P12*Inputs!$D$16/12, MAX(0, C13 - D13 - F13 - J13)), 0) -> 0 | O13: =IF(AND(H13=0, L13=0), MIN(P12, MAX(0, C13 - D13 - F13 - J13 - N13 - G13 - K13)), 0) -> 0 | P13: =MAX(0, P12 - O13) -> 0 | Q13: =IF(AND(E13=TRUE, I13=TRUE, M13=TRUE, A13<=Inputs!$C$20), R13, 0) -> 0 | R13: =MAX(0, C13 - D13 - F13 - J13 - N13 - G13 - K13 - O13) -> 0 | S13: =IF(ABS(D13+(F13+J13+N13)+(G13+K13+O13)+R13-C13)<1, "OK", "ERR") -> 0 | T13: =EDATE($T$2, A13) -> 0 | U13: =F13+G13 -> 0 | V13: =J13+K13 -> 0 | W13: =N13+O13 -> 0
A14: 12 | B14: ='Asset Side'!B13 -> 0 | C14: ='Asset Side'!J14+'Asset Side'!K14 -> 0 | D14: =MIN(C14, B13*Inputs!$C$21/12) -> 0 | E14: =IF(AND(B14 >= H13*Inputs!$C$27, Inputs!$C$31<>"Yes"), TRUE, FALSE) -> 0 | F14: =MIN(H13*Inputs!$D$14/12, MAX(0, C14 - D14)) -> 0 | G14: =MIN(H13, MAX(0, C14 - D14 - F14 - J14 - N14)) -> 0 | H14: =MAX(0, H13 - G14) -> 0 | I14: =IF(B14 >= (H13+L13)*Inputs!$C$28, TRUE, FALSE) -> 0 | J14: =IF(AND(E14=TRUE, A14<=Inputs!$C$20), MIN(L13*Inputs!$D$15/12, MAX(0, C14 - D14 - F14)), 0) -> 0 | K14: =IF(H14=0, MIN(L13, MAX(0, C14 - D14 - F14 - J14 - N14 - G14)), 0) -> 0 | L14: =MAX(0, L13 - K14) -> 0 | M14: =IF(B14 >= (H13+L13+P13)*Inputs!$C$29, TRUE, FALSE) -> 0 | N14: =IF(AND(I14=TRUE, A14<=Inputs!$C$20), MIN(P13*Inputs!$D$16/12, MAX(0, C14 - D14 - F14 - J14)), 0) -> 0 | O14: =IF(AND(H14=0, L14=0), MIN(P13, MAX(0, C14 - D14 - F14 - J14 - N14 - G14 - K14)), 0) -> 0 | P14: =MAX(0, P13 - O14) -> 0 | Q14: =IF(AND(E14=TRUE, I14=TRUE, M14=TRUE, A14<=Inputs!$C$20), R14, 0) -> 0 | R14: =MAX(0, C14 - D14 - F14 - J14 - N14 - G14 - K14 - O14) -> 0 | S14: =IF(ABS(D14+(F14+J14+N14)+(G14+K14+O14)+R14-C14)<1, "OK", "ERR") -> 0 | T14: =EDATE($T$2, A14) -> 0 | U14: =F14+G14 -> 0 | V14: =J14+K14 -> 0 | W14: =N14+O14 -> 0
... A82: 80 | B82: ='Asset Side'!B81 -> 0 | C82: ='Asset Side'!J82+'Asset Side'!K82 -> 0 | D82: =MIN(C82, B81*Inputs!$C$21/12) -> 0 | E82: =IF(AND(B82 >= H81*Inputs!$C$27, Inputs!$C$31<>"Yes"), TRUE, FALSE) -> 0 | F82: =MIN(H81*Inputs!$D$14/12, MAX(0, C82 - D82)) -> 0 | G82: =MIN(H81, MAX(0, C82 - D82 - F82 - J82 - N82)) -> 0 | H82: =MAX(0, H81 - G82) -> 0 | I82: =IF(B82 >= (H81+L81)*Inputs!$C$28, TRUE, FALSE) -> 0 | J82: =IF(AND(E82=TRUE, A82<=Inputs!$C$20), MIN(L81*Inputs!$D$15/12, MAX(0, C82 - D82 - F82)), 0) -> 0 | K82: =IF(H82=0, MIN(L81, MAX(0, C82 - D82 - F82 - J82 - N82 - G82)), 0) -> 0 | L82: =MAX(0, L81 - K82) -> 0 | M82: =IF(B82 >= (H81+L81+P81)*Inputs!$C$29, TRUE, FALSE) -> 0 | N82: =IF(AND(I82=TRUE, A82<=Inputs!$C$20), MIN(P81*Inputs!$D$16/12, MAX(0, C82 - D82 - F82 - J82)), 0) -> 0 | O82: =IF(AND(H82=0, L82=0), MIN(P81, MAX(0, C82 - D82 - F82 - J82 - N82 - G82 - K82)), 0) -> 0 | P82: =MAX(0, P81 - O82) -> 0 | Q82: =IF(AND(E82=TRUE, I82=TRUE, M82=TRUE, A82<=Inputs!$C$20), R82, 0) -> 0 | R82: =MAX(0, C82 - D82 - F82 - J82 - N82 - G82 - K82 - O82) -> 0 | S82: =IF(ABS(D82+(F82+J82+N82)+(G82+K82+O82)+R82-C82)<1, "OK", "ERR") -> 0 | T82: =EDATE($T$2, A82) -> 0 | U82: =F82+G82 -> 0 | V82: =J82+K82 -> 0 | W82: =N82+O82 -> 0

Sheet Bonds
B2: BOND RETURNS
B4: Metric | C4: Tranche A | D4: Tranche B | E4: Tranche C
B5: Initial Balance | C5: =Inputs!$C$6*Inputs!$C$14 -> 0 | D5: =Inputs!$C$6*Inputs!$C$15 -> 0 | E5: =Inputs!$C$6*Inputs!$C$16 -> 0
B6: Purchase Price | C6: =Inputs!$C$22 -> 0 | D6: =Inputs!$C$23 -> 0 | E6: =Inputs!$C$24 -> 0
B7: Investment ($) | C7: =C5*C6/100 -> 0 | D7: =D5*D6/100 -> 0 | E7: =E5*E6/100 -> 0
B8: Total CF Received | C8: =SUM(Waterfall!F:F)+SUM(Waterfall!G:G) -> 0 | D8: =SUM(Waterfall!J:J)+SUM(Waterfall!K:K) -> 0 | E8: =SUM(Waterfall!N:N)+SUM(Waterfall!O:O) -> 0
B9: PnL | C9: =C8-C7 -> 0 | D9: =D8-D7 -> 0 | E9: =E8-E7 -> 0
B11: XIRR | C11: =IFERROR(XIRR(Waterfall!U2:U82, Waterfall!T2:T82), "N/A") -> 0 | D11: =IFERROR(XIRR(Waterfall!V2:V82, Waterfall!T2:T82), "N/A") -> 0 | E11: =IFERROR(XIRR(Waterfall!W2:W82, Waterfall!T2:T82), "N/A") -> 0
B12: MOIC | C12: =IFERROR(C8/C7, 0) -> 0 | D12: =IFERROR(D8/D7, 0) -> 0 | E12: =IFERROR(E8/E7, 0) -> 0
B14: WAL (years) | C14: =IFERROR(SUMPRODUCT(Waterfall!G3:G82, Waterfall!A3:A82/12)/SUM(Waterfall!G3:G82), 0) -> 0 | D14: =IFERROR(SUMPRODUCT(Waterfall!K3:K82, Waterfall!A3:A82/12)/SUM(Waterfall!K3:K82), 0) -> 0 | E14: =IFERROR(SUMPRODUCT(Waterfall!O3:O82, Waterfall!A3:A82/12)/SUM(Waterfall!O3:O82), 0) -> 0
B15: Principal Received | C15: =SUM(Waterfall!G:G) -> 0 | D15: =SUM(Waterfall!K:K) -> 0 | E15: =SUM(Waterfall!O:O) -> 0
B16: Ending Balance | C16: =Waterfall!H82 -> 0 | D16: =Waterfall!L82 -> 0 | E16: =Waterfall!P82 -> 0
B17: Principal Loss | C17: =C16 -> 0 | D17: =D16 -> 0 | E17: =E16 -> 0
B18: Recovery Price | C18: =C15/C5*100 -> 0 | D18: =D15/D5*100 -> 0 | E18: =E15/E5*100 -> 0
B20: CREDIT ENHANCEMENT
B21: Initial CE % | C21: =1-Inputs!$C$14 -> 0 | D21: =1-Inputs!$C$14-Inputs!$C$15 -> 0 | E21: =1-Inputs!$C$14-Inputs!$C$15-Inputs!$C$16 -> 0
B22: Initial CE $ | C22: =Inputs!$C$6*C21 -> 0 | D22: =Inputs!$C$6*D21 -> 0 | E22: =Inputs!$C$6*E21 -> 0
B23: Remaining CE $ | C23: =MAX(0, C22 - MAX('Asset Side'!L:L)) -> 0 | D23: =MAX(0, D22 - MAX('Asset Side'!L:L)) -> 0 | E23: =MAX(0, E22 - MAX('Asset Side'!L:L)) -> 0
B24: Remaining CE % | C24: =IFERROR(C23/Inputs!$C$6, 0) -> 0 | D24: =IFERROR(D23/Inputs!$C$6, 0) -> 0 | E24: =IFERROR(E23/Inputs!$C$6, 0) -> 0
B25: Saturated? | C25: =IF(C17>0, "YES", "No") -> 0 | D25: =IF(D17>0, "YES", "No") -> 0 | E25: =IF(E17>0, "YES", "No") -> 0
B27: DIAGNOSTICS
B28: Pool CNL | C28: =MAX('Asset Side'!M:M) -> 0
B29: A OC Fail Months | C29: =COUNTIF(Waterfall!E:E, FALSE) -> 0
B30: B OC Fail Months | C30: =COUNTIF(Waterfall!I:I, FALSE) -> 0
B31: C OC Fail Months | C31: =COUNTIF(Waterfall!M:M, FALSE) -> 0
B32: Cash Check Errors | C32: =COUNTIF(Waterfall!S:S, "ERR") -> 0
B33: Total Trust Expenses | C33: =SUM(Waterfall!D:D) -> 0
B35: ASSUMPTIONS | C35: ="CPR "&TEXT(Inputs!$C$9,"0%")&" | CDR "&TEXT(Inputs!$C$10,"0%")&" | Sev "&TEXT(Inputs!$C$11,"0%") -> 0
B37: Change CDR (Inputs!C10) to stress test. Trust Expense (C21) defaults to 0.50% annual. OC fail OR post-ARD → excess turbos to senior principal.
